MANIFEST.in
README.md
setup.py
abrox/__init__.py
abrox.egg-info/PKG-INFO
abrox.egg-info/SOURCES.txt
abrox.egg-info/dependency_links.txt
abrox.egg-info/entry_points.txt
abrox.egg-info/requires.txt
abrox.egg-info/top_level.txt
abrox/core/__init__.py
abrox/core/abc.py
abrox/core/abc_config_check.py
abrox/core/abc_crossval.py
abrox/core/abc_initializer.py
abrox/core/abc_mcmc.py
abrox/core/abc_mcmc_plot.py
abrox/core/abc_model.py
abrox/core/abc_neural_net.py
abrox/core/abc_preprocess.py
abrox/core/abc_random_forest.py
abrox/core/abc_reference_table.py
abrox/core/abc_rejection.py
abrox/core/abc_report.py
abrox/core/abc_scale.py
abrox/core/abc_summary.py
abrox/core/abc_utils.py
abrox/core/abc_wegmann.py
abrox/gui/__init__.py
abrox/gui/a_console.py
abrox/gui/a_data_viewer.py
abrox/gui/a_dialogs.py
abrox/gui/a_editor.py
abrox/gui/a_exceptions.py
abrox/gui/a_main_window.py
abrox/gui/a_model.py
abrox/gui/a_priors.py
abrox/gui/a_process_manager.py
abrox/gui/a_pyconsole.py
abrox/gui/a_script_creator.py
abrox/gui/a_settings.py
abrox/gui/a_tree.py
abrox/gui/a_utils.py
abrox/gui/main.py
abrox/gui/tracksave.py
abrox/gui/icons/__init__.py
abrox/gui/icons/about.png
abrox/gui/icons/chain.png
abrox/gui/icons/clear.png
abrox/gui/icons/close.png
abrox/gui/icons/config.png
abrox/gui/icons/data.png
abrox/gui/icons/define.png
abrox/gui/icons/forest.png
abrox/gui/icons/function.png
abrox/gui/icons/help.png
abrox/gui/icons/icon.ico
abrox/gui/icons/load.png
abrox/gui/icons/loadsession.png
abrox/gui/icons/logo.png
abrox/gui/icons/model.png
abrox/gui/icons/newmodel.png
abrox/gui/icons/output.png
abrox/gui/icons/prior.png
abrox/gui/icons/priors.png
abrox/gui/icons/py.png
abrox/gui/icons/python_windows2.png
abrox/gui/icons/readme_logo.png
abrox/gui/icons/rejection.png
abrox/gui/icons/removemodel.png
abrox/gui/icons/run.png
abrox/gui/icons/savesession.png
abrox/gui/icons/settings.png
abrox/gui/icons/stop.png
abrox/gui/icons/undock.png
scripts/abrox-gui