Metadata-Version: 1.1
Name: abrox
Version: 2.0.2
Summary: A tool for Approximate Bayesian Computation
Home-page: https://github.com/mertensu/ABrox
Author: Ulf Mertens
Author-email: mertens.ulf@gmail.com
License: MIT
Download-URL: https://github.com/mertensu/ABrox/archive/0.1.tar.gz
Platform: UNKNOWN
